resnet_models/__init__.py
resnet_models/data_generator.py
resnet_models/main.py
resnet_models/metrics.py
resnet_models/settings.py
resnet_models/train.py
resnet_models/models/__init__.py
resnet_models/models/blocks.py
resnet_models/models/resnet_18.py
resnet_models/models/resnet_34.py
resnet_models/models/resnet_50.py
resnet_models-1.1.3.dist-info/LICENSE
resnet_models-1.1.3.dist-info/METADATA
resnet_models-1.1.3.dist-info/WHEEL
resnet_models-1.1.3.dist-info/entry_points.txt
resnet_models-1.1.3.dist-info/top_level.txt
resnet_models-1.1.3.dist-info/RECORD
